{
  "books": [
    {
      "author": "Nieznany",
      "title": "Testowy tytuł",
      "genre": "romance, thiller",
      "pages": "125",
      "image": "https://images-na.ssl-images-amazon.com/images/S/compressed.photo.goodreads.com/books/1659086907i/10964.jpg",
      "id": 11
    },
    {
      "author": "Diana Gabaldon",
      "title": "Obca",
      "genre": "romance, thiller",
      "pages": "500",
      "image": "https://images-na.ssl-images-amazon.com/images/S/compressed.photo.goodreads.com/books/1659086907i/10964.jpg",
      "id": 12
    },
    {
      "author": "Author nie wiem ale musi byc dlugie",
      "title": "Nastepny tytul ciekawej ksiazki ",
      "genre": "tez nie wiem ale robimy dlugi napis",
      "pages": "4234424234234",
      "image": "https://images.unsplash.com/photo-1576872381149-7847515ce5d8?ixlib=rb-4.0.3&ixid=M3wxMjA3fDB8MHxzZWFyY2h8NXx8Ym9va3xlbnwwfDF8MHx8fDA%3D&auto=format&fit=crop&w=900&q=60",
      "id": 13
    },
    {
      "author": "Diana Gabaldon",
      "title": "Obca 2",
      "genre": "romance, thiller",
      "pages": "465",
      "image": "https://images.unsplash.com/photo-1576872381149-7847515ce5d8?ixlib=rb-4.0.3&ixid=M3wxMjA3fDB8MHxzZWFyY2h8NXx8Ym9va3xlbnwwfDF8MHx8fDA%3D&auto=format&fit=crop&w=900&q=60",
      "id": 15
    },
    {
      "author": "v vcc",
      "title": "njjknkjnjnnnnknnjknknknnjnjnjn jnjbjkbkbb",
      "genre": "gvvgv",
      "pages": "6575",
      "image": "https://images.unsplash.com/photo-1576872381149-7847515ce5d8?ixlib=rb-4.0.3&ixid=M3wxMjA3fDB8MHxzZWFyY2h8NXx8Ym9va3xlbnwwfDF8MHx8fDA%3D&auto=format&fit=crop&w=900&q=60",
      "id": 16
    },
    {
      "author": "test",
      "title": "test",
      "genre": "test",
      "pages": "100",
      "image": "https://images.unsplash.com/photo-1576872381149-7847515ce5d8?ixlib=rb-4.0.3&ixid=M3wxMjA3fDB8MHxzZWFyY2h8NXx8Ym9va3xlbnwwfDF8MHx8fDA%3D&auto=format&fit=crop&w=900&q=60",
      "id": 17
    },
    {
      "author": "ggf",
      "title": "ftf",
      "genre": "gf",
      "pages": "4",
      "image": "https://images.unsplash.com/photo-1576872381149-7847515ce5d8?ixlib=rb-4.0.3&ixid=M3wxMjA3fDB8MHxzZWFyY2h8NXx8Ym9va3xlbnwwfDF8MHx8fDA%3D&auto=format&fit=crop&w=900&q=60",
      "id": 18
    },
    {
      "author": "Diana Gabaldon",
      "title": "Obca",
      "genre": "romance, thiller",
      "pages": "5",
      "image": "https://images.unsplash.com/photo-1576872381149-7847515ce5d8?ixlib=rb-4.0.3&ixid=M3wxMjA3fDB8MHxzZWFyY2h8NXx8Ym9va3xlbnwwfDF8MHx8fDA%3D&auto=format&fit=crop&w=900&q=60",
      "id": 19
    },
    {
      "author": "Diana Gabaldon",
      "title": "Obca",
      "genre": "romance, thiller",
      "pages": "6",
      "image": "",
      "id": 20
    },
    {
      "author": "Diana Gabaldon",
      "title": "Obca",
      "genre": "romance, thiller",
      "pages": "789",
      "image": "https://images.unsplash.com/photo-1576872381149-7847515ce5d8?ixlib=rb-4.0.3&ixid=M3wxMjA3fDB8MHxzZWFyY2h8NXx8Ym9va3xlbnwwfDF8MHx8fDA%3D&auto=format&fit=crop&w=900&q=60",
      "id": 21
    },
    {
      "author": "Diana Gabaldon",
      "title": "Obca",
      "genre": "romance, thiller",
      "pages": "7",
      "image": "",
      "id": 22
    }
  ],
  "test": [
    "ILoveReact!"
  ]
}